example.py
red_sysinfo/__init__.py
red_sysinfo/__main__.py
red_sysinfo/domain/__init__.py
red_sysinfo/domain/enums/__init__.py
red_sysinfo/domain/enums/platform/__init__.py
red_sysinfo/domain/enums/platform/cross_platform.py
red_sysinfo/domain/enums/platform/mac.py
red_sysinfo/domain/enums/platform/unix.py
red_sysinfo/domain/enums/platform/win32.py
red_sysinfo/domain/platform/__init__.py
red_sysinfo/domain/platform/methods.py
red_sysinfo/domain/platform/schemas.py
red_sysinfo/domain/platform/utils.py
red_sysinfo/utils/__init__.py
red_sysinfo/utils/platform_utils/__init__.py
red_sysinfo/utils/platform_utils/operations.py
red_sysinfo-0.1.2.dist-info/METADATA
red_sysinfo-0.1.2.dist-info/WHEEL
red_sysinfo-0.1.2.dist-info/top_level.txt
red_sysinfo-0.1.2.dist-info/RECORD
