Metadata-Version: 2.1
Name: red-sysinfo
Version: 0.1.2
Summary: Compile platform information from 'sys' and 'platform' modules into a single PLATFORM class.
Author-email: redjax <none@none.com>, redjax <jackenyon@gmail.com>
License: MIT
Project-URL: Repository, https://github.com/redjax/red-sysinfo
Requires-Python: >=3.11
